flatsurf/__init__.py
flatsurf/cache.py
flatsurf/features.py
flatsurf/version.py
flatsurf/geometry/__init__.py
flatsurf/geometry/chamanara.py
flatsurf/geometry/circle.py
flatsurf/geometry/cohomology.py
flatsurf/geometry/euclidean.py
flatsurf/geometry/finitely_generated_matrix_group.py
flatsurf/geometry/fundamental_group.py
flatsurf/geometry/gl2r_orbit_closure.py
flatsurf/geometry/homology.py
flatsurf/geometry/hyperbolic.py
flatsurf/geometry/interval_exchange_transformation.py
flatsurf/geometry/l_infinity_delaunay_cells.py
flatsurf/geometry/lazy.py
flatsurf/geometry/mappings.py
flatsurf/geometry/mega_wollmilchsau.py
flatsurf/geometry/minimal_cover.py
flatsurf/geometry/morphism.py
flatsurf/geometry/origami.py
flatsurf/geometry/polygon.py
flatsurf/geometry/polyhedra.py
flatsurf/geometry/pyflatsurf_conversion.py
flatsurf/geometry/similarity.py
flatsurf/geometry/similarity_surface_generators.py
flatsurf/geometry/straight_line_trajectory.py
flatsurf/geometry/subfield.py
flatsurf/geometry/surface.py
flatsurf/geometry/surface_legacy.py
flatsurf/geometry/surface_objects.py
flatsurf/geometry/tangent_bundle.py
flatsurf/geometry/thurston_veech.py
flatsurf/geometry/veech_group.py
flatsurf/geometry/categories/__init__.py
flatsurf/geometry/categories/cone_surfaces.py
flatsurf/geometry/categories/dilation_surfaces.py
flatsurf/geometry/categories/euclidean_polygonal_surfaces.py
flatsurf/geometry/categories/euclidean_polygons.py
flatsurf/geometry/categories/euclidean_polygons_with_angles.py
flatsurf/geometry/categories/half_translation_surfaces.py
flatsurf/geometry/categories/hyperbolic_polygons.py
flatsurf/geometry/categories/polygonal_surfaces.py
flatsurf/geometry/categories/polygons.py
flatsurf/geometry/categories/similarity_surfaces.py
flatsurf/geometry/categories/surface_category.py
flatsurf/geometry/categories/topological_surfaces.py
flatsurf/geometry/categories/translation_surfaces.py
flatsurf/geometry/pyflatsurf/conversion.py
flatsurf/geometry/pyflatsurf/morphism.py
sage_flatsurf-0.7.4.dist-info/METADATA
sage_flatsurf-0.7.4.dist-info/WHEEL
sage_flatsurf-0.7.4.dist-info/licenses/COPYING
sage_flatsurf-0.7.4.dist-info/RECORD
