Metadata-Version: 2.4
Name: sage-flatsurf
Version: 0.7.4
Summary: Flat surfaces in SageMath
Author: Vincent Delecroix, W. Patrick Hooper, Julian Rüth
License-File: COPYING
Keywords: Abelian differentials,Riemann surfaces,dynamics,flat surfaces,geometry,quadratic differentials,surfaces
Classifier: Development Status :: 4 - Beta
Classifier: Intended Audience :: Science/Research
Classifier: License :: OSI Approved :: GNU General Public License v2 or later (GPLv2+)
Classifier: Operating System :: OS Independent
Classifier: Programming Language :: Python
Classifier: Topic :: Scientific/Engineering :: Mathematics
Requires-Python: >=3.9
Requires-Dist: bidict
Requires-Dist: matplotlib
Requires-Dist: more-itertools
Requires-Dist: surface-dynamics<0.8.0,>=0.6.0
